{
  "annotations": { "list": [] },
  "editable": true,
  "fiscalYearStartMonth": 0,
  "graphTooltip": 1,
  "id": null,
  "links": [],
  "liveNow": false,
  "panels": [
    {
      "collapsed": false,
      "gridPos": { "h": 1, "w": 24, "x": 0, "y": 0 },
      "id": 1,
      "panels": [],
      "title": "Log Overview",
      "type": "row"
    },
    {
      "datasource": { "type": "grafana-azure-data-explorer-datasource", "uid": "adx-telemetry" },
      "fieldConfig": {
        "defaults": {
          "color": { "mode": "palette-classic" },
          "mappings": [],
          "thresholds": { "mode": "absolute", "steps": [{ "color": "green", "value": null }] },
          "unit": "short"
        },
        "overrides": []
      },
      "gridPos": { "h": 4, "w": 4, "x": 0, "y": 1 },
      "id": 2,
      "options": {
        "colorMode": "value",
        "graphMode": "area",
        "justifyMode": "auto",
        "orientation": "auto",
        "reduceOptions": { "calcs": ["lastNotNull"], "fields": "", "values": false },
        "textMode": "auto"
      },
      "targets": [{
        "database": "otel_demo",
        "datasource": { "type": "grafana-azure-data-explorer-datasource", "uid": "adx-telemetry" },
        "querySource": "raw",
        "rawMode": true,
        "query": "OTelLogs\n| extend Timestamp = ingestion_time()\n| where Timestamp > ago(1h)\n| count",
        "refId": "A",
        "resultFormat": "table",
        "queryType": "KQL"
      }],
      "title": "Total Logs",
      "type": "stat"
    },
    {
      "datasource": { "type": "grafana-azure-data-explorer-datasource", "uid": "adx-telemetry" },
      "fieldConfig": {
        "defaults": {
          "color": { "mode": "palette-classic" },
          "mappings": [],
          "thresholds": { "mode": "absolute", "steps": [{ "color": "green", "value": null }, { "color": "red", "value": 1 }] },
          "unit": "short"
        },
        "overrides": []
      },
      "gridPos": { "h": 4, "w": 4, "x": 4, "y": 1 },
      "id": 3,
      "options": {
        "colorMode": "value",
        "graphMode": "area",
        "justifyMode": "auto",
        "orientation": "auto",
        "reduceOptions": { "calcs": ["lastNotNull"], "fields": "", "values": false },
        "textMode": "auto"
      },
      "targets": [{
        "database": "otel_demo",
        "datasource": { "type": "grafana-azure-data-explorer-datasource", "uid": "adx-telemetry" },
        "querySource": "raw",
        "rawMode": true,
        "query": "OTelLogs\n| extend Timestamp = ingestion_time()\n| where Timestamp > ago(1h)\n| where SeverityText in ('ERROR', 'FATAL', 'Error', 'Fatal', 'error', 'fatal')\n| count",
        "refId": "A",
        "resultFormat": "table",
        "queryType": "KQL"
      }],
      "title": "Error Logs",
      "type": "stat"
    },
    {
      "datasource": { "type": "grafana-azure-data-explorer-datasource", "uid": "adx-telemetry" },
      "fieldConfig": {
        "defaults": {
          "color": { "mode": "palette-classic" },
          "mappings": [],
          "thresholds": { "mode": "absolute", "steps": [{ "color": "yellow", "value": null }] },
          "unit": "short"
        },
        "overrides": []
      },
      "gridPos": { "h": 4, "w": 4, "x": 8, "y": 1 },
      "id": 4,
      "options": {
        "colorMode": "value",
        "graphMode": "area",
        "justifyMode": "auto",
        "orientation": "auto",
        "reduceOptions": { "calcs": ["lastNotNull"], "fields": "", "values": false },
        "textMode": "auto"
      },
      "targets": [{
        "database": "otel_demo",
        "datasource": { "type": "grafana-azure-data-explorer-datasource", "uid": "adx-telemetry" },
        "querySource": "raw",
        "rawMode": true,
        "query": "OTelLogs\n| extend Timestamp = ingestion_time()\n| where Timestamp > ago(1h)\n| where SeverityText in ('WARN', 'WARNING', 'Warn', 'Warning', 'warn', 'warning')\n| count",
        "refId": "A",
        "resultFormat": "table",
        "queryType": "KQL"
      }],
      "title": "Warning Logs",
      "type": "stat"
    },
    {
      "datasource": { "type": "grafana-azure-data-explorer-datasource", "uid": "adx-telemetry" },
      "fieldConfig": {
        "defaults": {
          "color": { "mode": "palette-classic" },
          "mappings": [],
          "thresholds": { "mode": "absolute", "steps": [{ "color": "blue", "value": null }] },
          "unit": "short"
        },
        "overrides": []
      },
      "gridPos": { "h": 4, "w": 4, "x": 12, "y": 1 },
      "id": 5,
      "options": {
        "colorMode": "value",
        "graphMode": "area",
        "justifyMode": "auto",
        "orientation": "auto",
        "reduceOptions": { "calcs": ["lastNotNull"], "fields": "", "values": false },
        "textMode": "auto"
      },
      "targets": [{
        "database": "otel_demo",
        "datasource": { "type": "grafana-azure-data-explorer-datasource", "uid": "adx-telemetry" },
        "querySource": "raw",
        "rawMode": true,
        "query": "OTelLogs\n| extend Timestamp = ingestion_time()\n| where Timestamp > ago(1h)\n| where SeverityText in ('INFO', 'Info', 'info')\n| count",
        "refId": "A",
        "resultFormat": "table",
        "queryType": "KQL"
      }],
      "title": "Info Logs",
      "type": "stat"
    },
    {
      "datasource": { "type": "grafana-azure-data-explorer-datasource", "uid": "adx-telemetry" },
      "fieldConfig": {
        "defaults": {
          "color": { "mode": "palette-classic" },
          "mappings": [],
          "thresholds": { "mode": "absolute", "steps": [{ "color": "green", "value": null }] },
          "unit": "short"
        },
        "overrides": []
      },
      "gridPos": { "h": 4, "w": 4, "x": 16, "y": 1 },
      "id": 6,
      "options": {
        "colorMode": "value",
        "graphMode": "area",
        "justifyMode": "auto",
        "orientation": "auto",
        "reduceOptions": { "calcs": ["lastNotNull"], "fields": "", "values": false },
        "textMode": "auto"
      },
      "targets": [{
        "database": "otel_demo",
        "datasource": { "type": "grafana-azure-data-explorer-datasource", "uid": "adx-telemetry" },
        "querySource": "raw",
        "rawMode": true,
        "query": "OTelLogs\n| extend Timestamp = ingestion_time(), ServiceName = tostring(ResourceAttributes[\"service.name\"])\n| where Timestamp > ago(1h)\n| summarize dcount(ServiceName)",
        "refId": "A",
        "resultFormat": "table",
        "queryType": "KQL"
      }],
      "title": "Services Logging",
      "type": "stat"
    },
    {
      "datasource": { "type": "grafana-azure-data-explorer-datasource", "uid": "adx-telemetry" },
      "fieldConfig": {
        "defaults": {
          "color": { "mode": "palette-classic" },
          "mappings": [],
          "thresholds": { "mode": "absolute", "steps": [{ "color": "purple", "value": null }] },
          "unit": "short"
        },
        "overrides": []
      },
      "gridPos": { "h": 4, "w": 4, "x": 20, "y": 1 },
      "id": 7,
      "options": {
        "colorMode": "value",
        "graphMode": "area",
        "justifyMode": "auto",
        "orientation": "auto",
        "reduceOptions": { "calcs": ["lastNotNull"], "fields": "", "values": false },
        "textMode": "auto"
      },
      "targets": [{
        "database": "otel_demo",
        "datasource": { "type": "grafana-azure-data-explorer-datasource", "uid": "adx-telemetry" },
        "querySource": "raw",
        "rawMode": true,
        "query": "OTelLogs\n| extend Timestamp = ingestion_time()\n| where Timestamp > ago(1h)\n| where isnotempty(TraceId)\n| summarize dcount(TraceId)",
        "refId": "A",
        "resultFormat": "table",
        "queryType": "KQL"
      }],
      "title": "Correlated Traces",
      "type": "stat"
    },
    {
      "collapsed": false,
      "gridPos": { "h": 1, "w": 24, "x": 0, "y": 5 },
      "id": 8,
      "panels": [],
      "title": "Log Volume Over Time",
      "type": "row"
    },
    {
      "datasource": { "type": "grafana-azure-data-explorer-datasource", "uid": "adx-telemetry" },
      "fieldConfig": {
        "defaults": {
          "color": { "mode": "palette-classic" },
          "custom": {
            "axisCenteredZero": false,
            "axisColorMode": "text",
            "axisLabel": "",
            "axisPlacement": "auto",
            "barAlignment": 0,
            "drawStyle": "bars",
            "fillOpacity": 80,
            "gradientMode": "none",
            "hideFrom": { "legend": false, "tooltip": false, "viz": false },
            "lineInterpolation": "linear",
            "lineWidth": 1,
            "pointSize": 5,
            "scaleDistribution": { "type": "linear" },
            "showPoints": "never",
            "spanNulls": false,
            "stacking": { "group": "A", "mode": "normal" },
            "thresholdsStyle": { "mode": "off" }
          },
          "mappings": [],
          "thresholds": { "mode": "absolute", "steps": [{ "color": "green", "value": null }] },
          "unit": "short"
        },
        "overrides": [
          { "matcher": { "id": "byName", "options": "ERROR" }, "properties": [{ "id": "color", "value": { "fixedColor": "red", "mode": "fixed" } }] },
          { "matcher": { "id": "byName", "options": "WARN" }, "properties": [{ "id": "color", "value": { "fixedColor": "yellow", "mode": "fixed" } }] },
          { "matcher": { "id": "byName", "options": "INFO" }, "properties": [{ "id": "color", "value": { "fixedColor": "blue", "mode": "fixed" } }] },
          { "matcher": { "id": "byName", "options": "DEBUG" }, "properties": [{ "id": "color", "value": { "fixedColor": "green", "mode": "fixed" } }] }
        ]
      },
      "gridPos": { "h": 8, "w": 16, "x": 0, "y": 6 },
      "id": 9,
      "options": {
        "legend": { "calcs": ["sum"], "displayMode": "table", "placement": "bottom", "showLegend": true },
        "tooltip": { "mode": "multi", "sort": "desc" }
      },
      "targets": [{
        "database": "otel_demo",
        "datasource": { "type": "grafana-azure-data-explorer-datasource", "uid": "adx-telemetry" },
        "querySource": "raw",
        "rawMode": true,
        "query": "OTelLogs\n| extend Timestamp = ingestion_time()\n| where Timestamp > ago(1h)\n| extend Severity = case(\n    SeverityText in ('ERROR', 'FATAL', 'Error', 'Fatal'), 'ERROR',\n    SeverityText in ('WARN', 'WARNING', 'Warn', 'Warning'), 'WARN',\n    SeverityText in ('INFO', 'Info'), 'INFO',\n    SeverityText in ('DEBUG', 'Debug'), 'DEBUG',\n    'OTHER'\n)\n| summarize Count = count() by Severity, bin(Timestamp, 1m)\n| order by Timestamp asc",
        "refId": "A",
        "resultFormat": "time_series",
        "queryType": "KQL"
      }],
      "title": "Log Volume by Severity",
      "type": "timeseries"
    },
    {
      "datasource": { "type": "grafana-azure-data-explorer-datasource", "uid": "adx-telemetry" },
      "fieldConfig": {
        "defaults": {
          "color": { "mode": "palette-classic" },
          "mappings": [],
          "thresholds": { "mode": "absolute", "steps": [{ "color": "green", "value": null }] }
        },
        "overrides": []
      },
      "gridPos": { "h": 8, "w": 8, "x": 16, "y": 6 },
      "id": 10,
      "options": {
        "legend": { "displayMode": "table", "placement": "right", "showLegend": true, "values": ["value", "percent"] },
        "pieType": "donut",
        "reduceOptions": { "calcs": ["lastNotNull"], "fields": "", "values": false },
        "tooltip": { "mode": "single", "sort": "none" }
      },
      "targets": [{
        "database": "otel_demo",
        "datasource": { "type": "grafana-azure-data-explorer-datasource", "uid": "adx-telemetry" },
        "querySource": "raw",
        "rawMode": true,
        "query": "OTelLogs\n| extend Timestamp = ingestion_time()\n| where Timestamp > ago(1h)\n| extend Severity = case(\n    SeverityText in ('ERROR', 'FATAL', 'Error', 'Fatal'), 'ERROR',\n    SeverityText in ('WARN', 'WARNING', 'Warn', 'Warning'), 'WARN',\n    SeverityText in ('INFO', 'Info'), 'INFO',\n    SeverityText in ('DEBUG', 'Debug'), 'DEBUG',\n    'OTHER'\n)\n| summarize Count = count() by Severity",
        "refId": "A",
        "resultFormat": "table",
        "queryType": "KQL"
      }],
      "title": "Log Distribution by Severity",
      "type": "piechart"
    },
    {
      "collapsed": false,
      "gridPos": { "h": 1, "w": 24, "x": 0, "y": 14 },
      "id": 11,
      "panels": [],
      "title": "Logs by Service",
      "type": "row"
    },
    {
      "datasource": { "type": "grafana-azure-data-explorer-datasource", "uid": "adx-telemetry" },
      "fieldConfig": {
        "defaults": {
          "color": { "mode": "palette-classic" },
          "custom": {
            "axisCenteredZero": false,
            "axisColorMode": "text",
            "axisLabel": "",
            "axisPlacement": "auto",
            "barAlignment": 0,
            "drawStyle": "line",
            "fillOpacity": 20,
            "gradientMode": "opacity",
            "hideFrom": { "legend": false, "tooltip": false, "viz": false },
            "lineInterpolation": "smooth",
            "lineWidth": 2,
            "pointSize": 5,
            "scaleDistribution": { "type": "linear" },
            "showPoints": "never",
            "spanNulls": false,
            "stacking": { "group": "A", "mode": "none" },
            "thresholdsStyle": { "mode": "off" }
          },
          "mappings": [],
          "thresholds": { "mode": "absolute", "steps": [{ "color": "green", "value": null }] },
          "unit": "short"
        },
        "overrides": []
      },
      "gridPos": { "h": 8, "w": 12, "x": 0, "y": 15 },
      "id": 12,
      "options": {
        "legend": { "calcs": ["sum"], "displayMode": "table", "placement": "bottom", "showLegend": true },
        "tooltip": { "mode": "multi", "sort": "desc" }
      },
      "targets": [{
        "database": "otel_demo",
        "datasource": { "type": "grafana-azure-data-explorer-datasource", "uid": "adx-telemetry" },
        "querySource": "raw",
        "rawMode": true,
        "query": "OTelLogs\n| extend Timestamp = ingestion_time(), ServiceName = tostring(ResourceAttributes[\"service.name\"])\n| where Timestamp > ago(1h)\n| where isnotempty(ServiceName)\n| summarize Count = count() by ServiceName, bin(Timestamp, 1m)\n| order by Timestamp asc",
        "refId": "A",
        "resultFormat": "time_series",
        "queryType": "KQL"
      }],
      "title": "Log Volume by Service",
      "type": "timeseries"
    },
    {
      "datasource": { "type": "grafana-azure-data-explorer-datasource", "uid": "adx-telemetry" },
      "fieldConfig": {
        "defaults": {
          "color": { "mode": "thresholds" },
          "mappings": [],
          "thresholds": { "mode": "absolute", "steps": [{ "color": "green", "value": null }, { "color": "yellow", "value": 100 }, { "color": "red", "value": 500 }] },
          "unit": "short"
        },
        "overrides": []
      },
      "gridPos": { "h": 8, "w": 12, "x": 12, "y": 15 },
      "id": 13,
      "options": {
        "displayMode": "gradient",
        "minVizHeight": 10,
        "minVizWidth": 0,
        "orientation": "horizontal",
        "reduceOptions": { "calcs": ["lastNotNull"], "fields": "", "values": false },
        "showUnfilled": true,
        "valueMode": "color"
      },
      "targets": [{
        "database": "otel_demo",
        "datasource": { "type": "grafana-azure-data-explorer-datasource", "uid": "adx-telemetry" },
        "querySource": "raw",
        "rawMode": true,
        "query": "OTelLogs\n| extend Timestamp = ingestion_time(), ServiceName = tostring(ResourceAttributes[\"service.name\"])\n| where Timestamp > ago(1h)\n| where SeverityText in ('ERROR', 'FATAL', 'Error', 'Fatal')\n| where isnotempty(ServiceName)\n| summarize ErrorCount = count() by ServiceName\n| order by ErrorCount desc\n| take 15",
        "refId": "A",
        "resultFormat": "table",
        "queryType": "KQL"
      }],
      "title": "Top Services by Error Logs",
      "type": "bargauge"
    },
    {
      "collapsed": false,
      "gridPos": { "h": 1, "w": 24, "x": 0, "y": 23 },
      "id": 14,
      "panels": [],
      "title": "Error Log Details",
      "type": "row"
    },
    {
      "datasource": { "type": "grafana-azure-data-explorer-datasource", "uid": "adx-telemetry" },
      "fieldConfig": {
        "defaults": {
          "color": { "mode": "thresholds" },
          "custom": { "align": "auto", "cellOptions": { "type": "auto" }, "inspect": false },
          "mappings": [],
          "thresholds": { "mode": "absolute", "steps": [{ "color": "green", "value": null }] }
        },
        "overrides": [
          { "matcher": { "id": "byName", "options": "SeverityText" }, "properties": [{ "id": "custom.width", "value": 80 }] },
          { "matcher": { "id": "byName", "options": "ServiceName" }, "properties": [{ "id": "custom.width", "value": 150 }] },
          { "matcher": { "id": "byName", "options": "Timestamp" }, "properties": [{ "id": "custom.width", "value": 180 }] }
        ]
      },
      "gridPos": { "h": 12, "w": 24, "x": 0, "y": 24 },
      "id": 15,
      "options": {
        "cellHeight": "sm",
        "footer": { "countRows": false, "fields": "", "reducer": ["sum"], "show": false },
        "showHeader": true,
        "sortBy": [{ "desc": true, "displayName": "Timestamp" }]
      },
      "targets": [{
        "database": "otel_demo",
        "datasource": { "type": "grafana-azure-data-explorer-datasource", "uid": "adx-telemetry" },
        "querySource": "raw",
        "rawMode": true,
        "query": "OTelLogs\n| extend Timestamp = ingestion_time(), ServiceName = tostring(ResourceAttributes[\"service.name\"])\n| where Timestamp > ago(1h)\n| where SeverityText in ('ERROR', 'FATAL', 'Error', 'Fatal')\n| project Timestamp, SeverityText, ServiceName, Body, TraceId, SpanId\n| order by Timestamp desc\n| take 100",
        "refId": "A",
        "resultFormat": "table",
        "queryType": "KQL"
      }],
      "title": "Recent Error Logs",
      "type": "table"
    },
    {
      "collapsed": false,
      "gridPos": { "h": 1, "w": 24, "x": 0, "y": 36 },
      "id": 16,
      "panels": [],
      "title": "All Logs Stream",
      "type": "row"
    },
    {
      "datasource": { "type": "grafana-azure-data-explorer-datasource", "uid": "adx-telemetry" },
      "fieldConfig": {
        "defaults": {
          "color": { "mode": "thresholds" },
          "custom": { "align": "auto", "cellOptions": { "type": "auto" }, "inspect": false },
          "mappings": [],
          "thresholds": { "mode": "absolute", "steps": [{ "color": "green", "value": null }] }
        },
        "overrides": [
          { "matcher": { "id": "byName", "options": "Timestamp" }, "properties": [{ "id": "custom.width", "value": 180 }] },
          { "matcher": { "id": "byName", "options": "SeverityText" }, "properties": [{ "id": "custom.width", "value": 80 }] },
          { "matcher": { "id": "byName", "options": "ServiceName" }, "properties": [{ "id": "custom.width", "value": 150 }] }
        ]
      },
      "gridPos": { "h": 12, "w": 24, "x": 0, "y": 37 },
      "id": 17,
      "options": {
        "cellHeight": "sm",
        "footer": { "countRows": false, "fields": "", "reducer": ["sum"], "show": false },
        "showHeader": true,
        "sortBy": [{ "desc": true, "displayName": "Timestamp" }]
      },
      "targets": [{
        "database": "otel_demo",
        "datasource": { "type": "grafana-azure-data-explorer-datasource", "uid": "adx-telemetry" },
        "querySource": "raw",
        "rawMode": true,
        "query": "OTelLogs\n| extend Timestamp = ingestion_time(), ServiceName = tostring(ResourceAttributes[\"service.name\"])\n| where Timestamp > ago(15m)\n| project Timestamp, SeverityText, ServiceName, Body, TraceId\n| order by Timestamp desc\n| take 200",
        "refId": "A",
        "resultFormat": "table",
        "queryType": "KQL"
      }],
      "title": "Live Log Stream (Last 15 min)",
      "type": "table"
    }
  ],
  "refresh": "30s",
  "schemaVersion": 38,
  "style": "dark",
  "tags": ["opentelemetry", "azure", "adx", "logs"],
  "templating": { "list": [] },
  "time": { "from": "now-1h", "to": "now" },
  "timepicker": {},
  "timezone": "",
  "title": "ADX Logs Analytics",
  "uid": "adx-logs-analytics",
  "version": 1,
  "weekStart": ""
}
